{
  "package": "best.reich.ingrosware.mixin.impl",
  "refmap": "mixins.ingrosware.refmap.json",
  "target": "@env(DEFAULT)",
  "compatibilityLevel": "JAVA_8",
  "verbose": false,
  "mixins": [
    "client.entity.MixinAbstractClientPlayer",
    "block.MixinBlock",
    "network.packets.MixinCPacketCustomPayload",
    "network.packets.MixinCPacketPlayer",
    "network.packets.MixinCPacketTabComplete",
    "entity.MixinEntity",
    "entity.MixinEntityLivingBase",
    "entity.player.MixinEntityPlayer",
    "client.entity.MixinEntityPlayerSP",
    "client.renderer.MixinEntityRenderer",
    "client.gui.MixinFontRenderer",
    "client.settings.MixinGameSettings",
    "client.gui.MixinGuiBossOverlay",
    "client.gui.MixinGuiNewChat",
    "client.gui.MixinGuiScreen",
    "client.renderer.entity.MixinLayerArmorBase",
    "client.gui.MixinMainMenu",
    "client.MixinMinecraft",
    "util.MixinMovementInputFromOptions",
    "network.MixinNetHandlerPlayClient",
    "network.MixinNetworkManager",
    "client.multiplayer.MixinPlayerControllerMP",
    "client.renderer.entity.MixinRender",
    "client.renderer.entity.MixinRenderManager",
    "network.packets.MixinSPacketPosLook",
    "util.text.MixinTextComponentString",
    "world.MixinWorld",
    "client.multiplayer.MixinWorldClient"
  ]
}